[
  {
    "id": "p001",
    "name": "Sudadera Oversize Negra",
    "category": "sudadera",
    "tags": ["oversize", "urbano", "invierno", "casual"],
    "price": 39.99,
    "sizes": ["S", "M", "L", "XL"],
    "colors": ["negro"],
    "inStock": true,
    "popularity": 95,
    "url": "/tienda?categoria=camisas"
  },
  {
    "id": "p002",
    "name": "Camiseta Básica Blanca",
    "category": "camiseta",
    "tags": ["básico", "casual", "verano", "minimalista"],
    "price": 19.99,
    "sizes": ["XS", "S", "M", "L", "XL"],
    "colors": ["blanco"],
    "inStock": true,
    "popularity": 92,
    "url": "/tienda?categoria=camisas"
  },
  {
    "id": "p003",
    "name": "Pantalón Chino Beige",
    "category": "pantalon",
    "tags": ["elegante", "trabajo", "casual", "primavera"],
    "price": 49.99,
    "sizes": ["38", "40", "42", "44", "46"],
    "colors": ["beige"],
    "inStock": true,
    "popularity": 78,
    "url": "/tienda?categoria=pantalones"
  },
  {
    "id": "p004",
    "name": "Blazer Slim Fit Azul Marino",
    "category": "blazer",
    "tags": ["elegante", "trabajo", "formal", "evento"],
    "price": 89.99,
    "sizes": ["S", "M", "L", "XL"],
    "colors": ["azul marino"],
    "inStock": true,
    "popularity": 85,
    "url": "/tienda?categoria=trajes"
  },
  {
    "id": "p005",
    "name": "Jogger Deportivo Gris",
    "category": "pantalon",
    "tags": ["deportivo", "gym", "casual", "cómodo"],
    "price": 34.99,
    "sizes": ["S", "M", "L", "XL"],
    "colors": ["gris"],
    "inStock": true,
    "popularity": 88,
    "url": "/tienda?categoria=pantalones"
  },
  {
    "id": "p006",
    "name": "Camisa Oxford Celeste",
    "category": "camisa",
    "tags": ["elegante", "trabajo", "formal", "clásico"],
    "price": 44.99,
    "sizes": ["S", "M", "L", "XL", "XXL"],
    "colors": ["celeste", "azul claro"],
    "inStock": true,
    "popularity": 82,
    "url": "/tienda?categoria=camisas"
  },
  {
    "id": "p007",
    "name": "Abrigo Largo Negro",
    "category": "abrigo",
    "tags": ["elegante", "invierno", "formal", "evento"],
    "price": 129.99,
    "sizes": ["S", "M", "L", "XL"],
    "colors": ["negro"],
    "inStock": true,
    "popularity": 76,
    "url": "/tienda"
  },
  {
    "id": "p008",
    "name": "Polo Clásico Verde",
    "category": "polo",
    "tags": ["casual", "elegante", "verano", "golf"],
    "price": 29.99,
    "sizes": ["S", "M", "L", "XL"],
    "colors": ["verde"],
    "inStock": true,
    "popularity": 71,
    "url": "/tienda?categoria=camisas"
  },
  {
    "id": "p009",
    "name": "Sudadera con Capucha Gris",
    "category": "sudadera",
    "tags": ["urbano", "casual", "invierno", "cómodo"],
    "price": 45.99,
    "sizes": ["S", "M", "L", "XL", "XXL"],
    "colors": ["gris"],
    "inStock": true,
    "popularity": 90,
    "url": "/tienda?categoria=camisas"
  },
  {
    "id": "p010",
    "name": "Traje Completo Antracita",
    "category": "traje",
    "tags": ["formal", "elegante", "evento", "boda", "trabajo"],
    "price": 199.99,
    "sizes": ["46", "48", "50", "52", "54"],
    "colors": ["antracita", "gris oscuro"],
    "inStock": true,
    "popularity": 74,
    "url": "/tienda?categoria=trajes"
  },
  {
    "id": "p011",
    "name": "Camiseta Estampada Urbana",
    "category": "camiseta",
    "tags": ["urbano", "casual", "streetwear", "joven"],
    "price": 24.99,
    "sizes": ["S", "M", "L", "XL"],
    "colors": ["negro", "blanco"],
    "inStock": true,
    "popularity": 86,
    "url": "/tienda?categoria=camisas"
  },
  {
    "id": "p012",
    "name": "Chaqueta Bomber Marrón",
    "category": "chaqueta",
    "tags": ["urbano", "casual", "otoño", "retro"],
    "price": 79.99,
    "sizes": ["S", "M", "L", "XL"],
    "colors": ["marrón"],
    "inStock": false,
    "popularity": 80,
    "url": "/tienda"
  }
]
